lsst/__init__.py
lsst/daf/__init__.py
lsst/daf/butler/__init__.py
lsst/daf/butler/_butler.py
lsst/daf/butler/_butler_collections.py
lsst/daf/butler/_butler_config.py
lsst/daf/butler/_butler_instance_options.py
lsst/daf/butler/_butler_metrics.py
lsst/daf/butler/_butler_repo_index.py
lsst/daf/butler/_collection_type.py
lsst/daf/butler/_config.py
lsst/daf/butler/_config_support.py
lsst/daf/butler/_dataset_association.py
lsst/daf/butler/_dataset_existence.py
lsst/daf/butler/_dataset_provenance.py
lsst/daf/butler/_dataset_ref.py
lsst/daf/butler/_dataset_type.py
lsst/daf/butler/_deferredDatasetHandle.py
lsst/daf/butler/_exceptions.py
lsst/daf/butler/_exceptions_legacy.py
lsst/daf/butler/_file_dataset.py
lsst/daf/butler/_file_descriptor.py
lsst/daf/butler/_formatter.py
lsst/daf/butler/_labeled_butler_factory.py
lsst/daf/butler/_limited_butler.py
lsst/daf/butler/_location.py
lsst/daf/butler/_named.py
lsst/daf/butler/_quantum.py
lsst/daf/butler/_quantum_backed.py
lsst/daf/butler/_query_all_datasets.py
lsst/daf/butler/_registry_shim.py
lsst/daf/butler/_standalone_datastore.py
lsst/daf/butler/_storage_class.py
lsst/daf/butler/_storage_class_delegate.py
lsst/daf/butler/_timespan.py
lsst/daf/butler/_topology.py
lsst/daf/butler/_uuid.py
lsst/daf/butler/arrow_utils.py
lsst/daf/butler/column_spec.py
lsst/daf/butler/ddl.py
lsst/daf/butler/json.py
lsst/daf/butler/logging.py
lsst/daf/butler/mapping_factory.py
lsst/daf/butler/name_shrinker.py
lsst/daf/butler/nonempty_mapping.py
lsst/daf/butler/persistence_context.py
lsst/daf/butler/progress.py
lsst/daf/butler/py.typed
lsst/daf/butler/pydantic_utils.py
lsst/daf/butler/repo_relocation.py
lsst/daf/butler/time_utils.py
lsst/daf/butler/timespan_database_representation.py
lsst/daf/butler/utils.py
lsst/daf/butler/version.py
lsst/daf/butler/_rubin/__init__.py
lsst/daf/butler/_rubin/file_datasets.py
lsst/daf/butler/_rubin/temporary_for_ingest.py
lsst/daf/butler/_utilities/__init__.py
lsst/daf/butler/_utilities/locked_object.py
lsst_daf_butler-30.2026.300.dist-info/licenses/COPYRIGHT
lsst_daf_butler-30.2026.300.dist-info/licenses/LICENSE
lsst_daf_butler-30.2026.300.dist-info/licenses/bsd_license.txt
lsst_daf_butler-30.2026.300.dist-info/licenses/gpl-v3.0.txt
lsst_daf_butler-30.2026.300.dist-info/METADATA
lsst_daf_butler-30.2026.300.dist-info/WHEEL
lsst_daf_butler-30.2026.300.dist-info/entry_points.txt
lsst_daf_butler-30.2026.300.dist-info/top_level.txt
lsst_daf_butler-30.2026.300.dist-info/zip-safe
lsst_daf_butler-30.2026.300.dist-info/RECORD
