Metadata-Version: 2.4
Name: lsst-daf-butler
Version: 30.2026.300
Summary: An abstraction layer for reading and writing astronomical data to datastores.
Author-email: Rubin Observatory Data Management <dm-admin@lists.lsst.org>
License-Expression: BSD-3-Clause OR GPL-3.0-or-later
Project-URL: Homepage, https://github.com/lsst/daf_butler
Keywords: lsst
Classifier: Intended Audience :: Science/Research
Classifier: Operating System :: OS Independent
Classifier: Programming Language :: Python :: 3
Classifier: Programming Language :: Python :: 3.12
Classifier: Programming Language :: Python :: 3.11
Classifier: Programming Language :: Python :: 3.13
Classifier: Topic :: Scientific/Engineering :: Astronomy
Requires-Python: >=3.11.0
License-File: COPYRIGHT
License-File: LICENSE
License-File: bsd_license.txt
License-File: gpl-v3.0.txt
Requires-Dist: astropy>=7.0
Requires-Dist: pyyaml>=5.1
Requires-Dist: sqlalchemy>=1.4
Requires-Dist: click>=7.0
Requires-Dist: lsst-sphgeom
Requires-Dist: lsst-utils
Requires-Dist: lsst-resources
Requires-Dist: deprecated>=1.2
Requires-Dist: pydantic<3.0,>=2
Requires-Dist: pyarrow>=0.16
Requires-Dist: numpy
Provides-Extra: postgres
Requires-Dist: psycopg2; extra == "postgres"
Provides-Extra: remote
Requires-Dist: httpx; extra == "remote"
Requires-Dist: lsst-resources[https]; extra == "remote"
Provides-Extra: server
Requires-Dist: fastapi; extra == "server"
Requires-Dist: safir>=3.4.0; extra == "server"
Provides-Extra: test
Requires-Dist: pytest>=3.2; extra == "test"
Requires-Dist: numpy>=1.17; extra == "test"
Requires-Dist: matplotlib>=3.0.3; extra == "test"
Requires-Dist: pandas>=1.0; extra == "test"
Provides-Extra: s3
Requires-Dist: lsst-resources[s3]; extra == "s3"
Provides-Extra: https
Requires-Dist: lsst-resources[https]; extra == "https"
Provides-Extra: gs
Requires-Dist: lsst-resources[gs]; extra == "gs"
Dynamic: license-file
